ovos_PHAL_plugin_oauth/__init__.py
ovos_PHAL_plugin_oauth/version.py
ovos_PHAL_plugin_oauth-0.1.3.dist-info/LICENSE
ovos_PHAL_plugin_oauth-0.1.3.dist-info/METADATA
ovos_PHAL_plugin_oauth-0.1.3.dist-info/WHEEL
ovos_PHAL_plugin_oauth-0.1.3.dist-info/entry_points.txt
ovos_PHAL_plugin_oauth-0.1.3.dist-info/top_level.txt
ovos_PHAL_plugin_oauth-0.1.3.dist-info/zip-safe
ovos_PHAL_plugin_oauth-0.1.3.dist-info/RECORD
