Metadata-Version: 2.1
Name: ovos-PHAL-plugin-oauth
Version: 0.1.3
Summary: A plugin for OpenVoiceOS hardware abstraction layer
Home-page: https://github.com/OpenVoiceOS/ovos-PHAL-plugin-oauth
Author: JarbasAi
Author-email: jarbasai@mailfence.com
License: Apache-2.0
Platform: UNKNOWN
Classifier: Development Status :: 3 - Alpha
Classifier: Intended Audience :: Developers
Classifier: Topic :: Text Processing :: Linguistic
Classifier: License :: OSI Approved :: Apache Software License
Classifier: Programming Language :: Python :: 3.5
Classifier: Programming Language :: Python :: 3.6
Requires-Dist: ovos-utils<1.0.0,>=0.4.1
Requires-Dist: ovos-bus-client<2.0.0,>=0.0.3
Requires-Dist: Flask>=0.12
Requires-Dist: oauthlib~=3.0
Requires-Dist: qrcode[pil]~=7.3.1
